{
    "title": "Create Fund Price",
    "jsonPage": "viewFunds",
    "desciption": "",
    "pageType": "create",
    "fields": [{
        "name": "Funds",
        "type": "hiddendropdown",
        "tableRef": "funds",
        "placeholder": "Enter funds",
        "id": "input1",
        "validation": ["required", "trim", "unique"],
        "url": "funds/getAll"
    }, {
        "name": "Price",
        "type": "text",
        "tableRef": "price",
        "placeholder": "Enter name",
        "id": "input1",
        "validation": ["required", "trim", "unique"],
        "url": ""
    }],
    "action": [{
        "name": "submit",
        "action": "submitUser",
        "type":"type2",
        "submitUrl":"viewFundsPrice%C2%A2"
    }, {
        "name": "cancel",
        "type":"type2",
        "url":"viewFundsPrice%C2%A2"
    }],

    "apiCall": {
        "url": "fundsprice/save"
    },

    "sidemenu": [{
        "url": "",
        "anchor": "",
        "state": "",
        "action": ""
    }]
}
